nlp_preprocessing/__init__.py
nlp_preprocessing/clean.py
nlp_preprocessing/dataset.py
nlp_preprocessing/seq_parser_token_generator.py
nlp_preprocessing/seq_token_generator.py
nlp_preprocessing/tokenization.py
nlp_preprocessing/vocab_embedding_extractor.py
nlp_preprocessing-0.2.0.dist-info/METADATA
nlp_preprocessing-0.2.0.dist-info/WHEEL
nlp_preprocessing-0.2.0.dist-info/top_level.txt
nlp_preprocessing-0.2.0.dist-info/RECORD
