Metadata-Version: 2.1
Name: nlp-preprocessing
Version: 0.2.0
Summary: A Package for text preprocessing
Home-page: https://github.com/Ankur3107/nlp_preprocessing
Author: Ankur Singh
Author-email: ankur310794@gmail.com
License: UNKNOWN
Platform: UNKNOWN
Classifier: Programming Language :: Python :: 3
Classifier: License :: OSI Approved :: MIT License
Classifier: Operating System :: OS Independent
Requires-Dist: scikit-learn
Requires-Dist: gensim
Requires-Dist: numpy
Requires-Dist: spacy
Requires-Dist: deepdish
Requires-Dist: tqdm
